CHANGELOG.txt
LICENCE.txt
MANIFEST.in
README.txt
__int__.py
setup.py
dalab_01.egg-info/PKG-INFO
dalab_01.egg-info/SOURCES.txt
dalab_01.egg-info/dependency_links.txt
dalab_01.egg-info/top_level.txt