Metadata-Version: 2.1
Name: dalab-01
Version: 0.0.1
Summary: List of programs
Home-page: 
Author: Riyansh Prem
Author-email: riyansh969@gmail.com
License: MIT
Keywords: pro
Classifier: Development Status :: 5 - Production/Stable
Classifier: Intended Audience :: Education
Classifier: Operating System :: Microsoft :: Windows :: Windows 10
Classifier: License :: OSI Approved :: MIT License
Classifier: Programming Language :: Python :: 3
License-File: LICENCE.txt
